mini_cpu.v
module mini_cpu(input clk1, clk2);

    reg [31:0] Mem [1023:0];  //memory Rom - for instructions
    reg [31:0] Reg [31:0];  //32x32 registers

    reg [31:0] pc;       //program contrller
    reg [2:0] ID_EX_type, EX_MEM_type, MEM_WB_type;

    reg [31:0] IF_ID_IR;
    reg [31:0] ID_EX_IR, ID_EX_A, ID_EX_B, ID_EX_Imm;
    reg [31:0] EX_MEM_IR, EX_MEM_ALUout;
    reg [31:0] MEM_WB_IR, MEM_WB_ALUout;

    parameter ADD=6'b000000, SUB=6'b000001, MUL=6'b000010, AND=6'b000011, OR=6'b000100,
              ADDI=6'b000101, SUBI=6'b000110;

    parameter Rtype=3'b000, Itype=3'b001;

    always @(posedge clk1) begin    //IF Stage
        IF_ID_IR <= Mem[pc];
        pc <= pc+1;
    end

    always @(posedge clk2) begin    //ID Stage
        ID_EX_A <= Reg[IF_ID_IR[25:21]];
        ID_EX_B <= Reg[IF_ID_IR[20:16]];

        ID_EX_Imm <= {{16{IF_ID_IR[15]}},{IF_ID_IR[15:0]}};     //sign extended
        ID_EX_IR <= IF_ID_IR;

        case(IF_ID_IR[31:26])   //opcode decode
            ADD,SUB,MUL,AND,OR: ID_EX_type <= Rtype;
            ADDI,SUBI: ID_EX_type <= Itype;
        endcase
    end

    always @(posedge clk1) begin    //EX Stage
        EX_MEM_IR <= ID_EX_IR;
        EX_MEM_type <= ID_EX_type;

        case(ID_EX_type)
            Rtype:  case(ID_EX_IR[31:26])
                        ADD: EX_MEM_ALUout <= ID_EX_A + ID_EX_B;
                        SUB: EX_MEM_ALUout <= ID_EX_A - ID_EX_B;
                        MUL: EX_MEM_ALUout <= ID_EX_A * ID_EX_B;
                        AND: EX_MEM_ALUout <= ID_EX_A & ID_EX_B;
                        OR: EX_MEM_ALUout <= ID_EX_A | ID_EX_B;
                        default: EX_MEM_ALUout <= 32'hxxxxxxxx;
                    endcase
            Itype:  case(ID_EX_IR[31:26])
                        ADDI: EX_MEM_ALUout <= ID_EX_A + ID_EX_Imm;
                        SUBI: EX_MEM_ALUout <= ID_EX_A - ID_EX_Imm;
                        default: EX_MEM_ALUout <= 32'hxxxxxxxx;
                    endcase
        endcase
    end

    always @(posedge clk2) begin    //MEM Stage
        MEM_WB_IR <= EX_MEM_IR;
        MEM_WB_type <= EX_MEM_type;
        MEM_WB_ALUout <= EX_MEM_ALUout;
    end

    always @(posedge clk2) begin    //WB Stage
        case(MEM_WB_type)
            Rtype: Reg[MEM_WB_IR[15:11]] <= MEM_WB_ALUout;
            Itype: Reg[MEM_WB_IR[20:16]] <= MEM_WB_ALUout;
        endcase
    end
endmodule

mini_cpu_tb.v
`timescale 1ns/1ns
`include "mini_cpu.v"

module mini_cpu_tb();

    reg clk1, clk2;
    integer k;
    mini_cpu DUT(clk1, clk2);

    initial begin 
        clk1 = 0; clk2 = 0;
        $dumpfile("mini_cpu.vcd");
        $dumpvars(0, mini_cpu_tb);
    end

    // Clock toggling
    always begin
        #5 clk1 = ~clk1;
        #5 clk1 = ~clk1;
        #5 clk2 = ~clk2;
        #5 clk2 = ~clk2;
    end

    initial begin
        // Clear all registers
        for(k=0; k<=31; k=k+1)
            DUT.Reg[k] = 0;

        // Load Independent Instructions
        DUT.Mem[0] = 32'h14010005; // ADDI R1, R0, 5
        DUT.Mem[1] = 32'h14020007; // ADDI R2, R0, 7



        DUT.pc = 0;

        #600; // Wait for pipeline to finish

        // Display final register values
        $display("R1 (ADDI) = %d", DUT.Reg[1]);  // 5
        $display("R2 (ADDI) = %d", DUT.Reg[2]);  // 7
        $finish;
    end

endmodule

mini_cpu.vcd
$date
	Mon Jul 14 13:41:15 2025
$end
$version
	Icarus Verilog
$end
$timescale
	1ns
$end
$scope module mini_cpu_tb $end
$var reg 1 ! clk1 $end
$var reg 1 " clk2 $end
$var integer 32 # k [31:0] $end
$scope module DUT $end
$var wire 1 ! clk1 $end
$var wire 1 " clk2 $end
$var parameter 6 $ ADD $end
$var parameter 6 % ADDI $end
$var parameter 6 & AND $end
$var parameter 3 ' Itype $end
$var parameter 6 ( MUL $end
$var parameter 6 ) OR $end
$var parameter 3 * Rtype $end
$var parameter 6 + SUB $end
$var parameter 6 , SUBI $end
$var reg 32 - EX_MEM_ALUout [31:0] $end
$var reg 32 . EX_MEM_IR [31:0] $end
$var reg 3 / EX_MEM_type [2:0] $end
$var reg 32 0 ID_EX_A [31:0] $end
$var reg 32 1 ID_EX_B [31:0] $end
$var reg 32 2 ID_EX_IR [31:0] $end
$var reg 32 3 ID_EX_Imm [31:0] $end
$var reg 3 4 ID_EX_type [2:0] $end
$var reg 32 5 IF_ID_IR [31:0] $end
$var reg 32 6 MEM_WB_ALUout [31:0] $end
$var reg 32 7 MEM_WB_IR [31:0] $end
$var reg 3 8 MEM_WB_type [2:0] $end
$var reg 32 9 pc [31:0] $end
$upscope $end
$upscope $end
$enddefinitions $end
$comment Show the parameter values. $end
$dumpall
b110 ,
b1 +
b0 *
b100 )
b10 (
b1 '
b11 &
b101 %
b0 $
$end
#0
$dumpvars
b0 9
bx 8
bx 7
bx 6
bx 5
bx 4
bx 3
bx 2
bx 1
bx 0
bx /
bx .
bx -
b100000 #
0"
0!
$end
#5
b1 9
b10100000000010000000000000101 5
1!
#10
0!
#15
b1 4
b10100000000010000000000000101 2
b101 3
b0 1
b0 0
1"
#20
0"
#25
b101 -
b1 /
b10100000000010000000000000101 .
b10 9
b10100000000100000000000000111 5
1!
#30
0!
#35
b101 6
b1 8
b10100000000010000000000000101 7
b10100000000100000000000000111 2
b111 3
1"
#40
0"
#45
b11 9
bx 5
b111 -
b10100000000100000000000000111 .
1!
#50
0!
#55
bx 2
bx 3
bx 1
bx 0
b111 6
b10100000000100000000000000111 7
1"
#60
0"
#65
bx -
bx .
b100 9
1!
#70
0!
#75
bx 6
bx 7
1"
#80
0"
#85
b101 9
1!
#90
0!
#95
1"
#100
0"
#105
b110 9
1!
#110
0!
#115
1"
#120
0"
#125
b111 9
1!
#130
0!
#135
1"
#140
0"
#145
b1000 9
1!
#150
0!
#155
1"
#160
0"
#165
b1001 9
1!
#170
0!
#175
1"
#180
0"
#185
b1010 9
1!
#190
0!
#195
1"
#200
0"
#205
b1011 9
1!
#210
0!
#215
1"
#220
0"
#225
b1100 9
1!
#230
0!
#235
1"
#240
0"
#245
b1101 9
1!
#250
0!
#255
1"
#260
0"
#265
b1110 9
1!
#270
0!
#275
1"
#280
0"
#285
b1111 9
1!
#290
0!
#295
1"
#300
0"
#305
b10000 9
1!
#310
0!
#315
1"
#320
0"
#325
b10001 9
1!
#330
0!
#335
1"
#340
0"
#345
b10010 9
1!
#350
0!
#355
1"
#360
0"
#365
b10011 9
1!
#370
0!
#375
1"
#380
0"
#385
b10100 9
1!
#390
0!
#395
1"
#400
0"
#405
b10101 9
1!
#410
0!
#415
1"
#420
0"
#425
b10110 9
1!
#430
0!
#435
1"
#440
0"
#445
b10111 9
1!
#450
0!
#455
1"
#460
0"
#465
b11000 9
1!
#470
0!
#475
1"
#480
0"
#485
b11001 9
1!
#490
0!
#495
1"
#500
0"
#505
b11010 9
1!
#510
0!
#515
1"
#520
0"
#525
b11011 9
1!
#530
0!
#535
1"
#540
0"
#545
b11100 9
1!
#550
0!
#555
1"
#560
0"
#565
b11101 9
1!
#570
0!
#575
1"
#580
0"
#585
b11110 9
1!
